imagecraft/__init__.py
imagecraft/dynamic.py
imagecraft/presets.py
imagecraft/utils.py
imagecraft-0.2.4.dist-info/METADATA
imagecraft-0.2.4.dist-info/WHEEL
imagecraft-0.2.4.dist-info/top_level.txt
imagecraft-0.2.4.dist-info/RECORD
