Metadata-Version: 2.4
Name: imagecraft
Version: 0.2.4
Summary: Easy image resizing, cropping, and converting for Python and Django projects.
Author-email: Gin Li <qingge43@gmail.com>
License: MIT
Project-URL: Homepage, https://github.com/xgino/imagecraft
Project-URL: Documentation, https://github.com/xgino/imagecraft#readme
Requires-Python: >=3.8
Requires-Dist: pillow
